README.md
setup.py
ZeroCrawler/__init__.py
ZeroCrawler/api.py
ZeroCrawler/fetch.py
ZeroCrawler/models.py
ZeroCrawler/sessions.py
ZeroCrawler/utils.py
ZeroCrawler.egg-info/PKG-INFO
ZeroCrawler.egg-info/SOURCES.txt
ZeroCrawler.egg-info/dependency_links.txt
ZeroCrawler.egg-info/top_level.txt