Metadata-Version: 2.1
Name: ZeroCrawler
Version: 0.1.0
Summary: A small example package
Home-page: https://github.com/MeiK2333/ZeroCrawler
Author: MeiK2333
Author-email: meik2333@gmail.com
License: UNKNOWN
Platform: UNKNOWN
